Metadata-Version: 2.1
Name: dl-plus-extractor-un1def-ntsradio
Version: 0.2.0
Summary: A dl-plus extractor plugin for NTS Radio
Author-email: Dmitry Meyer <me@undef.im>
License: MIT
Project-URL: Homepage, https://github.com/un-def/dl-plus-extractor-un1def-ntsradio
Project-URL: Repository, https://github.com/un-def/dl-plus-extractor-un1def-ntsradio.git
Project-URL: Changelog, https://github.com/un-def/dl-plus-extractor-un1def-ntsradio/releases
Project-URL: Issues, https://github.com/un-def/dl-plus-extractor-un1def-ntsradio/issues
Requires-Python: >=3.8
License-File: LICENSE
Provides-Extra: dl-plus
Requires-Dist: dl-plus >=0.6.0 ; extra == 'dl-plus'
